nbmanips/__init__.py
nbmanips/__main__.py
nbmanips/exporters.py
nbmanips/cell/__init__.py
nbmanips/cell/cell_output.py
nbmanips/cell/cell_utils.py
nbmanips/cell/cells.py
nbmanips/cell/color.py
nbmanips/cell/output_parsers.py
nbmanips/cli/__init__.py
nbmanips/cli/collection.py
nbmanips/cli/convert.py
nbmanips/cli/explore.py
nbmanips/cli/select.py
nbmanips/cli/transform.py
nbmanips/notebook/__init__.py
nbmanips/notebook/dbc.py
nbmanips/notebook/ipynb.py
nbmanips/notebook/notebook.py
nbmanips/notebook/zpln.py
nbmanips/selector/__init__.py
nbmanips/selector/base_selectors.py
nbmanips/selector/callable_selector.py
nbmanips/selector/default_selector.py
nbmanips/selector/index_selector.py
nbmanips/selector/slice_selector.py
nbmanips-2.1.3.dist-info/METADATA
nbmanips-2.1.3.dist-info/WHEEL
nbmanips-2.1.3.dist-info/entry_points.txt
nbmanips-2.1.3.dist-info/licenses/LICENSE
nbmanips-2.1.3.dist-info/RECORD
