Metadata-Version: 2.4
Name: nbmanips
Version: 2.1.3
Summary: nbmanips allows you easily manipulate notebook files
Project-URL: Repository, https://github.com/hmiladhia/nbmanips.git
Project-URL: Issues, https://github.com/hmiladhia/nbmanips/issues
Author-email: Dhia Hmila <dhiahmila.dev@gmail.com>
Maintainer-email: Dhia Hmila <dhiahmila.dev@gmail.com>
License: MIT License
License-File: LICENSE
Keywords: dbc,ipynb,jupyter,notebook,notebooks,slides,zeppelin,zpln
Classifier: Development Status :: 5 - Production/Stable
Classifier: License :: OSI Approved :: MIT License
Classifier: Operating System :: OS Independent
Classifier: Programming Language :: Python :: 3
Requires-Python: >=3.9
Requires-Dist: auto-lazy-imports>=0.2.0
Requires-Dist: beautifulsoup4>=4.10.0
Requires-Dist: click>=7.1.0
Requires-Dist: cloudpickle>=1.6.0; python_version < '3.11'
Requires-Dist: cloudpickle>=2.1; python_version >= '3.11'
Requires-Dist: cloudpickle>=3.0; python_version >= '3.12'
Requires-Dist: colorama>=0.4.0
Requires-Dist: html2text==2020.1.16
Requires-Dist: lxml>=4.7.1
Requires-Dist: nbconvert>=6.0.0
Requires-Dist: nbformat>=5.1.3
Requires-Dist: pygments>=2.10
Requires-Dist: pyzmq>=24.0
Provides-Extra: images
Requires-Dist: img2text>=0.1.1; extra == 'images'
